setup.cfg
setup.py
authopenid_middleware/__init__.py
authopenid_middleware/authopenid.py
authopenid_middleware/mysqlrecycling.py
authopenid_middleware/parseurl.py
authopenid_middleware/sqlitedelayed.py
authopenid_middleware.egg-info/PKG-INFO
authopenid_middleware.egg-info/SOURCES.txt
authopenid_middleware.egg-info/dependency_links.txt
authopenid_middleware.egg-info/requires.txt
authopenid_middleware.egg-info/top_level.txt