Metadata-Version: 1.0
Name: authopenid-middleware
Version: 0.2.1
Summary: OpenID authentication middleware for WSGI applications
Home-page: http://trac.sandbox.lt/auth/wiki/AuthOpenIdMiddleware
Author: Dalius Dobravolskas
Author-email: dalius@sandbox.lt
License: MIT
Platform: UNKNOWN
